{
  "Workflows": [
    {
      "Path": null,
      "SortBy": 0,
      "VariablesSectionElementsOrder": [],
      "ArgumentsSectionElementsOrder": null,
      "ConstantsSectionElementsOrder": null,
      "AddedNamespaces": null
    },
    {
      "Path": "Main.xaml",
      "SortBy": 0,
      "VariablesSectionElementsOrder": [
        "InvoiceTotalDouble&TryCatch_1",
        "CompanyName&TryCatch_1",
        "ConvertInvoiceDate&TryCatch_1",
        "InvoiceNumber&TryCatch_1",
        "InvoiceNumberInt&TryCatch_1",
        "dt_Result&Sequence_1",
        "InvoiceTotal&Sequence_3",
        "InvoiceDate&Sequence_3"
      ],
      "ArgumentsSectionElementsOrder": [],
      "ConstantsSectionElementsOrder": null,
      "AddedNamespaces": null
    }
  ]
}